[
  {
    "id": 1,
    "ruc": "1675849302001",
    "company": "Sociedad Interamericana de fibras y alimentos",
    "provider_id": "18457542001",
    "client_provider": "Supermaxi CIA LTDA",
    "start_date": "15-08-2020",
    "solca": 324,
    "credit_cuota": 15,
    "interest_value": 4600,
    "default_interest": 1323,
    "invoice_number": "45657953413",
    "invoice_amount": 45908.23,
    "payment_date": "03-03-2021",
    "credit_operation_number": "92524",
    "credit_expiration_date": "02-07-2021",
    "default_days": 85,
    "status": "APROBADO"
  },
  {
    "id": 2,
    "ruc": "1675849302001",
    "company": "La internacional",
    "provider_id": "17457542001",
    "client_provider": "El Juri",
    "start_date": "03-08-2020",
    "solca": 234,
    "credit_cuota": 22,
    "interest_value": 669,
    "default_interest": 162,
    "invoice_number": "45678958543",
    "invoice_amount": 67876.21,
    "payment_date": "23-07-2021",
    "credit_operation_number": "92524",
    "credit_expiration_date": "14-10-2021",
    "default_days": 35,
    "status": "ANTICIPADO"
  },
  {
    "id": 3,
    "ruc": "1675849302001",
    "company": "KFC",
    "provider_id": "17457542001",
    "client_provider": "El Juri",
    "start_date": "14-09-2020",
    "solca": 4234,
    "credit_cuota": 12,
    "interest_value": 4443,
    "default_interest": 433,
    "invoice_number": "90877956783",
    "invoice_amount": 675908.23,
    "payment_date": "03-01-2021",
    "credit_operation_number": "92524",
    "credit_expiration_date": "17-05-2021",
    "default_days": 12,
    "status": "FINALIZADO"
  }
]
